hypergrep/__init__.py
hypergrep/multiscanner.py
hypergrep/scanner.py
hypergrep/utils.py
hypergrep/lib/__init__.py
hypergrep/lib/libhs.so.5.4.2
hypergrep/lib/libhyperscanner.so
hypergrep/lib/libzstd.so.1.5.5
hypergrep/lib/c/hyperscanner.c
hypergrep/lib/c/hyperscanner.h
hypergrep-3.2.0.dist-info/LICENSE
hypergrep-3.2.0.dist-info/METADATA
hypergrep-3.2.0.dist-info/WHEEL
hypergrep-3.2.0.dist-info/entry_points.txt
hypergrep-3.2.0.dist-info/top_level.txt
hypergrep-3.2.0.dist-info/RECORD
